{
  "created_at": "2025-10-08T03:28:32.346539+00:00",
  "elapsed": 0.195189,
  "encoding": "utf-8",
  "headers": {
    "CF-RAY": "98b28c790c343023-SJC",
    "Cache-Control": "max-age=1800",
    "Connection": "keep-alive",
    "Content-Encoding": "gzip",
    "Content-Type": "application\/json; charset=utf-8",
    "Date": "Wed, 08 Oct 2025 03:28:32 GMT",
    "Server": "cloudflare",
    "Transfer-Encoding": "chunked",
    "access-control-allow-credentials": "true",
    "access-control-allow-headers": "Authorization, Referer, Content-Type, User-Agent, Accept",
    "access-control-allow-methods": "GET, POST, PATCH, DELETE",
    "access-control-allow-origin": "*",
    "access-control-max-age": "604800",
    "alt-svc": "h3=\":443\"; ma=86400",
    "cf-cache-status": "DYNAMIC",
    "content-security-policy": "frame-ancestors *.makerbot.com *.thingiverse.com *.mbot.me *.onshape.com *.makerbot.local *.thingiverse.local;",
    "expires": "Wed, 08 Oct 2025 03:58:32 +0000",
    "speculation-rules": "\"\/cdn-cgi\/speculation\"",
    "vary": "Accept-Encoding, Authorization,Cookie"
  },
  "reason": "OK",
  "request": {
    "body": "",
    "cookies": {
      "__cf_bm": "MhlZ6cvBJxG8GzEi7AN7bdHb8Ij9s7sYi1tSWtC9cKg-1759894001-1.0.1.1-kAs29vIadw89WbSiM2azIkGN3o1qUuuLgs7iZJKMUrI_oOveXe1kFPy_HXDj4Iy1hJ40dScOS3FyoGAUgySF41_bf0Ic5EfJLh.of4Ie.TI",
      "_cfuvid": "UX1wOJNDtFxtuNbzhrgmm7lJWpOX4F4Tl.nlgyMQN7Q-1759894001214-0.0.1.1-604800000"
    },
    "headers": {
      "Accept": "*\/*",
      "Accept-Encoding": "gzip, deflate, br, zstd",
      "Connection": "keep-alive",
      "Cookie": "__cf_bm=MhlZ6cvBJxG8GzEi7AN7bdHb8Ij9s7sYi1tSWtC9cKg-1759894001-1.0.1.1-kAs29vIadw89WbSiM2azIkGN3o1qUuuLgs7iZJKMUrI_oOveXe1kFPy_HXDj4Iy1hJ40dScOS3FyoGAUgySF41_bf0Ic5EfJLh.of4Ie.TI; _cfuvid=UX1wOJNDtFxtuNbzhrgmm7lJWpOX4F4Tl.nlgyMQN7Q-1759894001214-0.0.1.1-604800000",
      "User-Agent": "python-requests\/2.32.3"
    },
    "method": "GET",
    "url": "https:\/\/api.thingiverse.com\/things\/3713140?access_token=REDACTED"
  },
  "status_code": 200,
  "url": "https:\/\/api.thingiverse.com\/things\/3713140?access_token=REDACTED",
  "_decoded_content": {
    "id": 3713140,
    "name": "Geometric Solid Builder",
    "thumbnail": "https:\/\/cdn.thingiverse.com\/renders\/da\/28\/65\/b7\/97\/7dae5b85a0fcd82a9adb39f55d514b18_display_large.jpg",
    "url": "https:\/\/api.thingiverse.com\/things\/3713140",
    "public_url": "https:\/\/www.thingiverse.com\/thing:3713140",
    "creator": {
      "id": 2652477,
      "name": "ntaufscar",
      "first_name": "NTA",
      "last_name": "UFSCar Campus Sorocaba",
      "url": "https:\/\/api.thingiverse.com\/users\/ntaufscar",
      "public_url": "https:\/\/www.thingiverse.com\/ntaufscar",
      "thumbnail": "https:\/\/cdn.thingiverse.com\/renders\/9e\/78\/64\/6b\/10\/0677fe0ca2f244ce0c2264d6557c3057_thumb_medium.jpg",
      "count_of_followers": 8,
      "count_of_following": 0,
      "count_of_designs": 10,
      "collection_count": 1,
      "make_count": 0,
      "accepts_tips": false,
      "is_following": false,
      "location": "Sorocaba, S\u00e3o Paulo, Brazil",
      "cover": "https:\/\/cdn.thingiverse.com\/renders\/fb\/1e\/a8\/f6\/84\/d62608f0b1b91c7c29beb0b93c3a3ba8_preview_large.jpg",
      "is_admin": false,
      "is_moderator": false,
      "is_featured": false,
      "is_verified": false
    },
    "added": "2019-06-25T17:40:24+00:00",
    "modified": "2019-06-25T17:40:24+00:00",
    "is_published": 1,
    "is_wip": 1,
    "is_featured": false,
    "is_nsfw": false,
    "is_ai": false,
    "is_winner": false,
    "is_edu_approved": false,
    "is_printable": false,
    "like_count": 3,
    "is_liked": false,
    "collect_count": 4,
    "is_collected": false,
    "comment_count": 0,
    "is_watched": false,
    "default_image": {
      "id": 11042532,
      "url": "https:\/\/cdn.thingiverse.com\/assets\/6c\/b8\/76\/f9\/84\/Foto.png",
      "name": "Foto.png",
      "sizes": [
        {
          "type": "thumb",
          "size": "large",
          "url": "https:\/\/cdn.thingiverse.com\/renders\/da\/28\/65\/b7\/97\/7dae5b85a0fcd82a9adb39f55d514b18_thumb_large.jpg"
        },
        {
          "type": "thumb",
          "size": "medium",
          "url": "https:\/\/cdn.thingiverse.com\/renders\/da\/28\/65\/b7\/97\/7dae5b85a0fcd82a9adb39f55d514b18_thumb_medium.jpg"
        },
        {
          "type": "thumb",
          "size": "small",
          "url": "https:\/\/cdn.thingiverse.com\/renders\/da\/28\/65\/b7\/97\/7dae5b85a0fcd82a9adb39f55d514b18_thumb_small.jpg"
        },
        {
          "type": "thumb",
          "size": "tiny",
          "url": "https:\/\/cdn.thingiverse.com\/renders\/da\/28\/65\/b7\/97\/7dae5b85a0fcd82a9adb39f55d514b18_thumb_tiny.jpg"
        },
        {
          "type": "preview",
          "size": "featured",
          "url": "https:\/\/cdn.thingiverse.com\/renders\/da\/28\/65\/b7\/97\/7dae5b85a0fcd82a9adb39f55d514b18_preview_featured.jpg"
        },
        {
          "type": "preview",
          "size": "card",
          "url": "https:\/\/cdn.thingiverse.com\/renders\/da\/28\/65\/b7\/97\/7dae5b85a0fcd82a9adb39f55d514b18_preview_card.jpg"
        },
        {
          "type": "preview",
          "size": "large",
          "url": "https:\/\/cdn.thingiverse.com\/renders\/da\/28\/65\/b7\/97\/7dae5b85a0fcd82a9adb39f55d514b18_preview_large.jpg"
        },
        {
          "type": "preview",
          "size": "medium",
          "url": "https:\/\/cdn.thingiverse.com\/renders\/da\/28\/65\/b7\/97\/7dae5b85a0fcd82a9adb39f55d514b18_preview_medium.jpg"
        },
        {
          "type": "preview",
          "size": "small",
          "url": "https:\/\/cdn.thingiverse.com\/renders\/da\/28\/65\/b7\/97\/7dae5b85a0fcd82a9adb39f55d514b18_preview_small.jpg"
        },
        {
          "type": "preview",
          "size": "birdwing",
          "url": "https:\/\/cdn.thingiverse.com\/renders\/da\/28\/65\/b7\/97\/7dae5b85a0fcd82a9adb39f55d514b18_preview_birdwing.jpg"
        },
        {
          "type": "preview",
          "size": "tiny",
          "url": "https:\/\/cdn.thingiverse.com\/renders\/da\/28\/65\/b7\/97\/7dae5b85a0fcd82a9adb39f55d514b18_preview_tiny.jpg"
        },
        {
          "type": "preview",
          "size": "tinycard",
          "url": "https:\/\/cdn.thingiverse.com\/renders\/da\/28\/65\/b7\/97\/7dae5b85a0fcd82a9adb39f55d514b18_preview_tinycard.jpg"
        },
        {
          "type": "display",
          "size": "large",
          "url": "https:\/\/cdn.thingiverse.com\/renders\/da\/28\/65\/b7\/97\/7dae5b85a0fcd82a9adb39f55d514b18_display_large.jpg"
        },
        {
          "type": "display",
          "size": "medium",
          "url": "https:\/\/cdn.thingiverse.com\/renders\/da\/28\/65\/b7\/97\/7dae5b85a0fcd82a9adb39f55d514b18_display_medium.jpg"
        },
        {
          "type": "display",
          "size": "small",
          "url": "https:\/\/cdn.thingiverse.com\/renders\/da\/28\/65\/b7\/97\/7dae5b85a0fcd82a9adb39f55d514b18_display_small.jpg"
        }
      ],
      "added": "2019-06-25T17:40:20+00:00"
    },
    "description": "In order to use the device it is necessary to employ barbecue wood sticks.\r\n\r\nALL TEXTS ARE IN PORTUGUESE.\r\n\r\nThis assistive technology was developed by the Research and Development Group of Assistive Technology of the Federal University of S\u00e3o Carlos (NTA\/UFSCar\/Sorocaba), Brazil.\r\n\r\nThe research group thanks the National Council for Scientific and Technological Development (CNPq) for the funding of the Vert\u00e1til Project (Process No. 442261\/2016-0), the research collaborators and the State Education Network of Sorocaba.",
    "instructions": "",
    "description_html": "<div><p>In order to use the device it is necessary to employ barbecue wood sticks.<\/p><p>ALL TEXTS ARE IN PORTUGUESE.<\/p><p>This assistive technology was developed by the Research and Development Group of Assistive Technology of the Federal University of S\u00e3o Carlos (NTA\/UFSCar\/Sorocaba), Brazil.<\/p><p>The research group thanks the National Council for Scientific and Technological Development (CNPq) for the funding of the Vert\u00e1til Project (Process No. 442261\/2016-0), the research collaborators and the State Education Network of Sorocaba.<\/p><\/div>",
    "instructions_html": "<div><\/div>",
    "details": "<div><h1 class=\"thing-component-header summary summary\">Summary<\/h1><div><p>In order to use the device it is necessary to employ barbecue wood sticks.<\/p><p>ALL TEXTS ARE IN PORTUGUESE.<\/p><p>This assistive technology was developed by the Research and Development Group of Assistive Technology of the Federal University of S\u00e3o Carlos (NTA\/UFSCar\/Sorocaba), Brazil.<\/p><p>The research group thanks the National Council for Scientific and Technological Development (CNPq) for the funding of the Vert\u00e1til Project (Process No. 442261\/2016-0), the research collaborators and the State Education Network of Sorocaba.<\/p><\/div><h1 class=\"thing-component-header settings print-settings\">Print Settings<\/h1><p class=\"detail-setting printer\"><strong>Printer: <\/strong>                         <\/p><div><p>Raise 3D N2<\/p><\/div>                                    <pre><code>                                            &lt;p class=\"detail-setting rafts\"&gt;&lt;strong&gt;Rafts: &lt;\/strong&gt;                     &lt;div&gt;&lt;p&gt;Yes&lt;\/p&gt;&lt;\/div&gt;&lt;\/p&gt;                                                                                &lt;p class=\"detail-setting supports\"&gt;&lt;strong&gt;Supports: &lt;\/strong&gt;                     &lt;div&gt;&lt;p&gt;Yes&lt;\/p&gt;&lt;\/div&gt;&lt;\/p&gt;                                                                                &lt;p class=\"detail-setting resolution\"&gt;&lt;strong&gt;Resolution: &lt;\/strong&gt;                     &lt;div&gt;&lt;p&gt;Normal&lt;\/p&gt;&lt;\/div&gt;&lt;\/p&gt;                                                                                &lt;p class=\"detail-setting infill\"&gt;&lt;strong&gt;Infill: &lt;\/strong&gt;                     &lt;div&gt;&lt;p&gt;85 to 100%&lt;\/p&gt;&lt;\/div&gt;&lt;\/p&gt;                                                    &lt;strong&gt;Filament:&lt;\/strong&gt; 3D Fila ABS<\/code><\/pre><\/div>",
    "details_parts": [
      {
        "type": "summary",
        "name": "Summary",
        "required": "required",
        "data": [
          {
            "content": "<div><p>In order to use the device it is necessary to employ barbecue wood sticks.<\/p><p>ALL TEXTS ARE IN PORTUGUESE.<\/p><p>This assistive technology was developed by the Research and Development Group of Assistive Technology of the Federal University of S\u00e3o Carlos (NTA\/UFSCar\/Sorocaba), Brazil.<\/p><p>The research group thanks the National Council for Scientific and Technological Development (CNPq) for the funding of the Vert\u00e1til Project (Process No. 442261\/2016-0), the research collaborators and the State Education Network of Sorocaba.<\/p><\/div>"
          }
        ]
      },
      {
        "type": "settings",
        "name": "Print Settings",
        "data": [
          {
            "printer": "<div><p>Raise 3D N2<\/p><\/div>",
            "rafts": "Yes",
            "supports": "Yes",
            "resolution": "<div><p>Normal<\/p><\/div>",
            "infill": "<div><p>85 to 100%<\/p><\/div>",
            "filament_brand": "<div><p>3D Fila<\/p><\/div>",
            "filament_material": "<div><p>ABS<\/p><\/div>"
          }
        ]
      },
      {
        "type": "tips",
        "name": "Post-Printing"
      },
      {
        "type": "design",
        "name": "How I Designed This"
      },
      {
        "type": "custom",
        "name": "Custom Section"
      }
    ],
    "edu_details": "",
    "edu_details_parts": [
      {
        "type": "grades",
        "name": "Grade",
        "required": "recommended",
        "save_as_component": false,
        "template": "taglist_select",
        "fieldname": "grades",
        "default": "Choose a range, help teachers see if this is a fit for their class",
        "opts": {
          "15": "Kindergarten",
          "16": "1st Grade",
          "17": "2nd Grade",
          "18": "3rd Grade",
          "19": "4th Grade",
          "20": "5th Grade",
          "21": "6th Grade",
          "22": "7th Grade",
          "23": "8th Grade",
          "24": "9th Grade",
          "25": "10th Grade",
          "26": "11th Grade",
          "27": "12th Grade",
          "28": "Higher Education"
        }
      },
      {
        "type": "subjects",
        "name": "Subject",
        "required": "recommended",
        "save_as_component": false,
        "template": "taglist_select",
        "fieldname": "subjects",
        "default": "Choose a Subject, Make your project more findable",
        "opts": {
          "11": "Science",
          "12": "Math",
          "13": "Engineering",
          "14": "History",
          "15": "Geography",
          "16": "Art",
          "17": "Languages",
          "18": "Music",
          "19": "Technology",
          "20": "Special Ed"
        }
      },
      {
        "type": "standards",
        "name": "Standards",
        "required": "recommended",
        "save_as_component": false,
        "template": "taglist_select",
        "fieldname": "standards",
        "default": "Choose a Requirement this lesson meets",
        "opts": {
          "3": "NGSS",
          "4": "CCSS"
        }
      },
      {
        "type": "overview",
        "name": "Overview and Background",
        "required": "required"
      },
      {
        "type": "plan",
        "name": "Lesson Plan and Activity",
        "required": "required"
      },
      {
        "type": "materials",
        "name": "Materials Needed",
        "required": "recommended"
      },
      {
        "type": "skills",
        "name": "Skills Learned",
        "label": "Enter each skill and press enter to add it as a tagged skill",
        "required": false,
        "template": "taglist",
        "fieldname": "skills",
        "default": "Choose Skills",
        "opts": []
      },
      {
        "type": "duration",
        "name": "Duration of Lesson",
        "template": "textfield"
      },
      {
        "type": "prep",
        "name": "Preparation"
      },
      {
        "type": "assets",
        "name": "Handouts and Assets",
        "save_as_component": false,
        "label": "Upload any files, docs, etc. They will be found under the Files tab on the Thing Page.",
        "template": "upload"
      },
      {
        "type": "assessment",
        "name": "Rubric and Assessment"
      },
      {
        "type": "references",
        "name": "References"
      }
    ],
    "license": "Creative Commons - Attribution - Non-Commercial - Share Alike",
    "allows_derivatives": true,
    "files_url": "https:\/\/api.thingiverse.com\/things\/3713140\/files",
    "images_url": "https:\/\/api.thingiverse.com\/things\/3713140\/images",
    "likes_url": "https:\/\/api.thingiverse.com\/things\/3713140\/likes",
    "ancestors_url": "https:\/\/api.thingiverse.com\/things\/3713140\/ancestors",
    "derivatives_url": "https:\/\/api.thingiverse.com\/things\/3713140\/derivatives",
    "tags_url": "https:\/\/api.thingiverse.com\/things\/3713140\/tags",
    "tags": [
      {
        "name": "mathematics",
        "tag": "mathematics",
        "url": "https:\/\/api.thingiverse.com\/tags\/mathematics",
        "count": 846,
        "things_url": "https:\/\/api.thingiverse.com\/tags\/mathematics\/things",
        "absolute_url": "\/tag:mathematics"
      },
      {
        "name": "socket",
        "tag": "socket",
        "url": "https:\/\/api.thingiverse.com\/tags\/socket",
        "count": 1653,
        "things_url": "https:\/\/api.thingiverse.com\/tags\/socket\/things",
        "absolute_url": "\/tag:socket"
      },
      {
        "name": "Solid Geometric",
        "tag": "solid_geometric",
        "url": "https:\/\/api.thingiverse.com\/tags\/solid_geometric",
        "count": 1,
        "things_url": "https:\/\/api.thingiverse.com\/tags\/solid_geometric\/things",
        "absolute_url": "\/tag:Solid_Geometric"
      }
    ],
    "categories_url": "https:\/\/api.thingiverse.com\/things\/3713140\/categories",
    "file_count": 1,
    "is_private": 0,
    "is_purchased": 0,
    "app_id": null,
    "download_count": 210,
    "view_count": 279,
    "education": {
      "grades": {
        "19": "4th Grade",
        "20": "5th Grade",
        "21": "6th Grade",
        "22": "7th Grade",
        "23": "8th Grade"
      },
      "subjects": [
        {
          "name": "Math",
          "slug": "math",
          "id": 12
        },
        {
          "name": "Special Ed",
          "slug": "special-ed",
          "id": 20
        }
      ]
    },
    "remix_count": 0,
    "make_count": 0,
    "app_count": 4,
    "root_comment_count": 0,
    "moderation": "",
    "is_derivative": false,
    "ancestors": [],
    "type_name": "Thing",
    "is_banned": false,
    "is_comments_disabled": false,
    "needs_moderation": 0,
    "is_decoy": 0,
    "zip_data": {
      "files": [
        {
          "name": "4mmSocket.stl",
          "url": "https:\/\/cdn.thingiverse.com\/assets\/1d\/2c\/10\/61\/6b\/4mmSocket.stl"
        }
      ],
      "images": [
        {
          "name": "Foto.png",
          "url": "https:\/\/cdn.thingiverse.com\/assets\/6c\/b8\/76\/f9\/84\/Foto.png"
        },
        {
          "name": "fd9c58a5309740e3f9106a7deb4a9b8a.png",
          "url": "https:\/\/cdn.thingiverse.com\/renders\/02\/f6\/d4\/9b\/e1\/fd9c58a5309740e3f9106a7deb4a9b8a.png"
        }
      ]
    }
  }
}