{
  "created_at": "2025-04-10T03:34:59.243353+00:00",
  "elapsed": 0.153698,
  "encoding": "utf-8",
  "headers": {
    "CF-RAY": "92df310b5b052a21-ORD",
    "Cache-Control": "max-age=1800",
    "Connection": "keep-alive",
    "Content-Encoding": "gzip",
    "Content-Type": "application\/json; charset=utf-8",
    "Date": "Thu, 10 Apr 2025 03:34:59 GMT",
    "Server": "cloudflare",
    "Transfer-Encoding": "chunked",
    "access-control-allow-credentials": "true",
    "access-control-allow-headers": "Authorization, Referer, Content-Type, User-Agent, Accept",
    "access-control-allow-methods": "GET, POST, PATCH, DELETE",
    "access-control-allow-origin": "*",
    "access-control-max-age": "604800",
    "alt-svc": "h3=\":443\"; ma=86400",
    "cf-cache-status": "DYNAMIC",
    "content-security-policy": "frame-ancestors *.makerbot.com *.thingiverse.com *.mbot.me *.onshape.com *.makerbot.local *.thingiverse.local;",
    "expires": "Thu, 10 Apr 2025 04:04:59 +0000",
    "speculation-rules": "\"\/cdn-cgi\/speculation\"",
    "vary": "Accept-Encoding, Authorization,Cookie"
  },
  "reason": "OK",
  "request": {
    "body": "",
    "cookies": {
      "__cf_bm": "SoihpvFH0wTUQtZEx3N82TZTnvYxxlvYaNi.s7dbO3s-1744255829-1.0.1.1-eCm3Elix6_zbC1A0CvmP.YDpxkWJbIYDKioQIINQdmO1Rpewrzk.IGUjOSFl24351CZ1KDXAxBWAgD0QCbBuRPWJZK7ecNfGHFatnnB2r0g",
      "_cfuvid": "u4gMHfeQEOqM9eTM.mGAM4IQ1Z.8jZtQXYCbjlUIvMY-1744255829433-0.0.1.1-604800000"
    },
    "headers": {
      "Accept": "*\/*",
      "Accept-Encoding": "gzip, deflate, br, zstd",
      "Connection": "keep-alive",
      "Cookie": "__cf_bm=SoihpvFH0wTUQtZEx3N82TZTnvYxxlvYaNi.s7dbO3s-1744255829-1.0.1.1-eCm3Elix6_zbC1A0CvmP.YDpxkWJbIYDKioQIINQdmO1Rpewrzk.IGUjOSFl24351CZ1KDXAxBWAgD0QCbBuRPWJZK7ecNfGHFatnnB2r0g; _cfuvid=u4gMHfeQEOqM9eTM.mGAM4IQ1Z.8jZtQXYCbjlUIvMY-1744255829433-0.0.1.1-604800000",
      "User-Agent": "python-requests\/2.32.3"
    },
    "method": "GET",
    "url": "https:\/\/api.thingiverse.com\/things\/4978254?access_token=REDACTED"
  },
  "status_code": 200,
  "url": "https:\/\/api.thingiverse.com\/things\/4978254?access_token=REDACTED",
  "_decoded_content": {
    "id": 4978254,
    "name": "Mouth Stick Holder for Loc line",
    "thumbnail": "https:\/\/cdn.thingiverse.com\/assets\/91\/ad\/f8\/32\/2b\/large_display_Locline_mouthstick_holder.JPG",
    "url": "https:\/\/api.thingiverse.com\/things\/4978254",
    "public_url": "https:\/\/www.thingiverse.com\/thing:4978254",
    "creator": {
      "id": 2625419,
      "name": "mattwhiteAT",
      "first_name": "Matt",
      "last_name": "White",
      "url": "https:\/\/api.thingiverse.com\/users\/mattwhiteAT",
      "public_url": "https:\/\/www.thingiverse.com\/mattwhiteAT",
      "thumbnail": "https:\/\/cdn.thingiverse.com\/site\/img\/default\/avatar\/avatar_professional_thumb_medium.jpg",
      "count_of_followers": 4,
      "count_of_following": 19,
      "count_of_designs": 4,
      "collection_count": 2,
      "make_count": 0,
      "accepts_tips": false,
      "is_following": false,
      "location": "",
      "cover": "https:\/\/cdn.thingiverse.com\/site\/img\/default\/cover\/cover-10_preview_large.jpg",
      "is_admin": false,
      "is_moderator": false,
      "is_featured": false,
      "is_verified": false
    },
    "added": "2021-09-30T14:33:11+00:00",
    "modified": "2021-09-30T14:33:11+00:00",
    "is_published": 1,
    "is_wip": 0,
    "is_featured": false,
    "is_nsfw": false,
    "is_ai": false,
    "is_winner": false,
    "is_edu_approved": false,
    "is_printable": false,
    "like_count": 4,
    "is_liked": false,
    "collect_count": 10,
    "is_collected": false,
    "comment_count": 0,
    "is_watched": false,
    "default_image": {
      "id": 16084054,
      "url": "https:\/\/cdn.thingiverse.com\/assets\/df\/db\/22\/12\/da\/Locline_mouthstick_holder.JPG",
      "name": "Locline_mouthstick_holder.JPG",
      "sizes": [
        {
          "type": "thumb",
          "size": "large",
          "url": "https:\/\/cdn.thingiverse.com\/assets\/e2\/0d\/72\/f7\/ca\/large_thumb_Locline_mouthstick_holder.JPG"
        },
        {
          "type": "thumb",
          "size": "medium",
          "url": "https:\/\/cdn.thingiverse.com\/assets\/d8\/64\/37\/bc\/6d\/medium_thumb_Locline_mouthstick_holder.JPG"
        },
        {
          "type": "thumb",
          "size": "small",
          "url": "https:\/\/cdn.thingiverse.com\/assets\/13\/f2\/0c\/f4\/4d\/small_thumb_Locline_mouthstick_holder.JPG"
        },
        {
          "type": "thumb",
          "size": "tiny",
          "url": "https:\/\/cdn.thingiverse.com\/assets\/da\/fd\/4b\/53\/d0\/tiny_thumb_Locline_mouthstick_holder.JPG"
        },
        {
          "type": "preview",
          "size": "featured",
          "url": "https:\/\/cdn.thingiverse.com\/assets\/21\/c1\/03\/78\/4e\/featured_preview_Locline_mouthstick_holder.JPG"
        },
        {
          "type": "preview",
          "size": "card",
          "url": "https:\/\/cdn.thingiverse.com\/assets\/ed\/34\/56\/7b\/e6\/card_preview_Locline_mouthstick_holder.JPG"
        },
        {
          "type": "preview",
          "size": "large",
          "url": "https:\/\/cdn.thingiverse.com\/assets\/5f\/8d\/75\/90\/ce\/large_preview_Locline_mouthstick_holder.JPG"
        },
        {
          "type": "preview",
          "size": "medium",
          "url": "https:\/\/cdn.thingiverse.com\/assets\/b8\/00\/b7\/e4\/69\/medium_preview_Locline_mouthstick_holder.JPG"
        },
        {
          "type": "preview",
          "size": "small",
          "url": "https:\/\/cdn.thingiverse.com\/assets\/77\/0e\/9a\/28\/07\/small_preview_Locline_mouthstick_holder.JPG"
        },
        {
          "type": "preview",
          "size": "birdwing",
          "url": "https:\/\/cdn.thingiverse.com\/assets\/03\/2d\/b5\/75\/de\/birdwing_preview_Locline_mouthstick_holder.JPG"
        },
        {
          "type": "preview",
          "size": "tiny",
          "url": "https:\/\/cdn.thingiverse.com\/assets\/03\/d0\/14\/2f\/f2\/tiny_preview_Locline_mouthstick_holder.JPG"
        },
        {
          "type": "preview",
          "size": "tinycard",
          "url": "https:\/\/cdn.thingiverse.com\/assets\/7e\/28\/47\/64\/58\/tinycard_preview_Locline_mouthstick_holder.JPG"
        },
        {
          "type": "display",
          "size": "large",
          "url": "https:\/\/cdn.thingiverse.com\/assets\/91\/ad\/f8\/32\/2b\/large_display_Locline_mouthstick_holder.JPG"
        },
        {
          "type": "display",
          "size": "medium",
          "url": "https:\/\/cdn.thingiverse.com\/assets\/f1\/c0\/22\/7b\/c2\/medium_display_Locline_mouthstick_holder.JPG"
        },
        {
          "type": "display",
          "size": "small",
          "url": "https:\/\/cdn.thingiverse.com\/assets\/08\/ff\/b9\/40\/82\/small_display_Locline_mouthstick_holder.JPG"
        }
      ],
      "added": "2021-09-30T14:32:00+00:00"
    },
    "description": "Simple Mouth Stick holder with loc line male end. Attach to loc line and clamps from Modularhose.com \r\n\r\n",
    "instructions": "",
    "description_html": "<div><p>Simple Mouth Stick holder with loc line male end. Attach to loc line and clamps from Modularhose.com <\/p><\/div>\n",
    "instructions_html": "<div><\/div>\n",
    "details": "<div><h1 class=\"thing-component-header summary summary\">Summary<\/h1><div><p>Simple Mouth Stick holder with loc line male end. Attach to loc line and clamps from Modularhose.com <\/p><\/div><h1 class=\"thing-component-header settings print-settings\">Print Settings<\/h1><p class=\"detail-setting printer brand\"><strong>Printer Brand: <\/strong>                         <\/p><div><p>Stratasys<\/p><\/div>                                    <pre><code>                                            &lt;p class=\"detail-setting printer\"&gt;&lt;strong&gt;Printer: &lt;\/strong&gt;                     &lt;div&gt;&lt;p&gt;F370&lt;\/p&gt;&lt;\/div&gt;<\/code><\/pre><p><\/p>                                    <p class=\"detail-setting supports\"><strong>Supports: <\/strong>                         <\/p><div><p>No<\/p><\/div><h1 class=\"thing-component-header design how-i-designed-this\">How I Designed This<\/h1><p class=\"detail-image\"><img src=\"https:\/\/.s3.amazonaws.com\/?AWSAccessKeyId=AKIAJ4LU5KWCMM7WB7YA&amp;Expires=1632312852&amp;Signature=yaGB07mMG3Im%2F5OpG32x6YoOZBM%3D\" alt=\"image\"><\/p><pre><code>                &lt;p class=\"detail-image\"&gt;&lt;img src=\"https:\/\/.s3.amazonaws.com\/?AWSAccessKeyId=AKIAJ4LU5KWCMM7WB7YA&amp;Expires=1632312853&amp;Signature=JuKgZiqb5Pa7wGLDthGG%2B%2BV2Rzc%3D\"&gt;&lt;\/p&gt;                &lt;p class=\"detail-image\"&gt;&lt;img src=\"https:\/\/.s3.amazonaws.com\/?AWSAccessKeyId=AKIAJ4LU5KWCMM7WB7YA&amp;Expires=1632312854&amp;Signature=3RbezCiSZA2Jk4q8nJ8dL4Ap8dE%3D\"&gt;&lt;\/p&gt;                &lt;p class=\"detail-image\"&gt;&lt;img src=\"https:\/\/.s3.amazonaws.com\/?AWSAccessKeyId=AKIAJ4LU5KWCMM7WB7YA&amp;Expires=1632312854&amp;Signature=3RbezCiSZA2Jk4q8nJ8dL4Ap8dE%3D\"&gt;&lt;\/p&gt;                &lt;p class=\"detail-image\"&gt;&lt;img src=\"https:\/\/.s3.amazonaws.com\/?AWSAccessKeyId=AKIAJ4LU5KWCMM7WB7YA&amp;Expires=1632312855&amp;Signature=llkv9vUgDf9SACVxP6fXdlBgKKg%3D\"&gt;&lt;\/p&gt;                &lt;p class=\"detail-image\"&gt;&lt;img src=\"https:\/\/.s3.amazonaws.com\/?AWSAccessKeyId=AKIAJ4LU5KWCMM7WB7YA&amp;Expires=1632312855&amp;Signature=llkv9vUgDf9SACVxP6fXdlBgKKg%3D\"&gt;&lt;\/p&gt;<\/code><\/pre><\/div>\n",
    "details_parts": [
      {
        "type": "summary",
        "name": "Summary",
        "required": "required",
        "data": [
          {
            "content": "<div><p>Simple Mouth Stick holder with loc line male end. Attach to loc line and clamps from Modularhose.com <\/p><\/div>\n"
          }
        ]
      },
      {
        "type": "settings",
        "name": "Print Settings",
        "data": [
          {
            "printer brand": "<div><p>Stratasys<\/p><\/div>\n",
            "printer": "<div><p>F370<\/p><\/div>\n",
            "supports": "No"
          }
        ]
      },
      {
        "type": "tips",
        "name": "Post-Printing"
      },
      {
        "type": "design",
        "name": "How I Designed This",
        "data": [
          {
            "image": "https:\/\/.s3.amazonaws.com\/?AWSAccessKeyId=AKIAJ4LU5KWCMM7WB7YA&Expires=1632312852&Signature=yaGB07mMG3Im%2F5OpG32x6YoOZBM%3D",
            "image_id": "667538"
          },
          {
            "image": "https:\/\/.s3.amazonaws.com\/?AWSAccessKeyId=AKIAJ4LU5KWCMM7WB7YA&Expires=1632312853&Signature=JuKgZiqb5Pa7wGLDthGG%2B%2BV2Rzc%3D",
            "image_id": "667540"
          },
          {
            "image": "https:\/\/.s3.amazonaws.com\/?AWSAccessKeyId=AKIAJ4LU5KWCMM7WB7YA&Expires=1632312854&Signature=3RbezCiSZA2Jk4q8nJ8dL4Ap8dE%3D",
            "image_id": "667545"
          },
          {
            "image": "https:\/\/.s3.amazonaws.com\/?AWSAccessKeyId=AKIAJ4LU5KWCMM7WB7YA&Expires=1632312854&Signature=3RbezCiSZA2Jk4q8nJ8dL4Ap8dE%3D",
            "image_id": "667546"
          },
          {
            "image": "https:\/\/.s3.amazonaws.com\/?AWSAccessKeyId=AKIAJ4LU5KWCMM7WB7YA&Expires=1632312855&Signature=llkv9vUgDf9SACVxP6fXdlBgKKg%3D",
            "image_id": "667548"
          },
          {
            "image": "https:\/\/.s3.amazonaws.com\/?AWSAccessKeyId=AKIAJ4LU5KWCMM7WB7YA&Expires=1632312855&Signature=llkv9vUgDf9SACVxP6fXdlBgKKg%3D",
            "image_id": "667549"
          }
        ]
      },
      {
        "type": "custom",
        "name": "Custom Section"
      }
    ],
    "edu_details": "",
    "edu_details_parts": [
      {
        "type": "grades",
        "name": "Grade",
        "required": "recommended",
        "save_as_component": false,
        "template": "taglist_select",
        "fieldname": "grades",
        "default": "Choose a range, help teachers see if this is a fit for their class",
        "opts": {
          "15": "Kindergarten",
          "16": "1st Grade",
          "17": "2nd Grade",
          "18": "3rd Grade",
          "19": "4th Grade",
          "20": "5th Grade",
          "21": "6th Grade",
          "22": "7th Grade",
          "23": "8th Grade",
          "24": "9th Grade",
          "25": "10th Grade",
          "26": "11th Grade",
          "27": "12th Grade",
          "28": "Higher Education"
        }
      },
      {
        "type": "subjects",
        "name": "Subject",
        "required": "recommended",
        "save_as_component": false,
        "template": "taglist_select",
        "fieldname": "subjects",
        "default": "Choose a Subject, Make your project more findable",
        "opts": {
          "11": "Science",
          "12": "Math",
          "13": "Engineering",
          "14": "History",
          "15": "Geography",
          "16": "Art",
          "17": "Languages",
          "18": "Music",
          "19": "Technology",
          "20": "Special Ed"
        }
      },
      {
        "type": "standards",
        "name": "Standards",
        "required": "recommended",
        "save_as_component": false,
        "template": "taglist_select",
        "fieldname": "standards",
        "default": "Choose a Requirement this lesson meets",
        "opts": {
          "3": "NGSS",
          "4": "CCSS"
        }
      },
      {
        "type": "overview",
        "name": "Overview and Background",
        "required": "required"
      },
      {
        "type": "plan",
        "name": "Lesson Plan and Activity",
        "required": "required"
      },
      {
        "type": "materials",
        "name": "Materials Needed",
        "required": "recommended"
      },
      {
        "type": "skills",
        "name": "Skills Learned",
        "label": "Enter each skill and press enter to add it as a tagged skill",
        "required": false,
        "template": "taglist",
        "fieldname": "skills",
        "default": "Choose Skills",
        "opts": []
      },
      {
        "type": "duration",
        "name": "Duration of Lesson",
        "template": "textfield"
      },
      {
        "type": "prep",
        "name": "Preparation"
      },
      {
        "type": "assets",
        "name": "Handouts and Assets",
        "save_as_component": false,
        "label": "Upload any files, docs, etc. They will be found under the Files tab on the Thing Page.",
        "template": "upload"
      },
      {
        "type": "assessment",
        "name": "Rubric and Assessment"
      },
      {
        "type": "references",
        "name": "References"
      }
    ],
    "license": "Creative Commons - Attribution",
    "allows_derivatives": true,
    "files_url": "https:\/\/api.thingiverse.com\/things\/4978254\/files",
    "images_url": "https:\/\/api.thingiverse.com\/things\/4978254\/images",
    "likes_url": "https:\/\/api.thingiverse.com\/things\/4978254\/likes",
    "ancestors_url": "https:\/\/api.thingiverse.com\/things\/4978254\/ancestors",
    "derivatives_url": "https:\/\/api.thingiverse.com\/things\/4978254\/derivatives",
    "tags_url": "https:\/\/api.thingiverse.com\/things\/4978254\/tags",
    "tags": [
      {
        "name": "accessibility",
        "tag": "accessibility",
        "url": "https:\/\/api.thingiverse.com\/tags\/accessibility",
        "count": 568,
        "things_url": "https:\/\/api.thingiverse.com\/tags\/accessibility\/things",
        "absolute_url": "\/tag:accessibility"
      },
      {
        "name": "assistive technology",
        "tag": "assistive_technology",
        "url": "https:\/\/api.thingiverse.com\/tags\/assistive_technology",
        "count": 620,
        "things_url": "https:\/\/api.thingiverse.com\/tags\/assistive_technology\/things",
        "absolute_url": "\/tag:assistive_technology"
      },
      {
        "name": "disability",
        "tag": "disability",
        "url": "https:\/\/api.thingiverse.com\/tags\/disability",
        "count": 533,
        "things_url": "https:\/\/api.thingiverse.com\/tags\/disability\/things",
        "absolute_url": "\/tag:disability"
      },
      {
        "name": "disabled",
        "tag": "disabled",
        "url": "https:\/\/api.thingiverse.com\/tags\/disabled",
        "count": 274,
        "things_url": "https:\/\/api.thingiverse.com\/tags\/disabled\/things",
        "absolute_url": "\/tag:disabled"
      },
      {
        "name": "limited mobility",
        "tag": "limited_mobility",
        "url": "https:\/\/api.thingiverse.com\/tags\/limited_mobility",
        "count": 39,
        "things_url": "https:\/\/api.thingiverse.com\/tags\/limited_mobility\/things",
        "absolute_url": "\/tag:limited_mobility"
      },
      {
        "name": "occupational therapy",
        "tag": "occupational_therapy",
        "url": "https:\/\/api.thingiverse.com\/tags\/occupational_therapy",
        "count": 431,
        "things_url": "https:\/\/api.thingiverse.com\/tags\/occupational_therapy\/things",
        "absolute_url": "\/tag:occupational_therapy"
      },
      {
        "name": "rehabilitation",
        "tag": "rehabilitation",
        "url": "https:\/\/api.thingiverse.com\/tags\/rehabilitation",
        "count": 123,
        "things_url": "https:\/\/api.thingiverse.com\/tags\/rehabilitation\/things",
        "absolute_url": "\/tag:rehabilitation"
      },
      {
        "name": "spinal cord injury",
        "tag": "spinal_cord_injury",
        "url": "https:\/\/api.thingiverse.com\/tags\/spinal_cord_injury",
        "count": 36,
        "things_url": "https:\/\/api.thingiverse.com\/tags\/spinal_cord_injury\/things",
        "absolute_url": "\/tag:spinal_cord_injury"
      },
      {
        "name": "wheelchair",
        "tag": "wheelchair",
        "url": "https:\/\/api.thingiverse.com\/tags\/wheelchair",
        "count": 400,
        "things_url": "https:\/\/api.thingiverse.com\/tags\/wheelchair\/things",
        "absolute_url": "\/tag:wheelchair"
      }
    ],
    "categories_url": "https:\/\/api.thingiverse.com\/things\/4978254\/categories",
    "file_count": 1,
    "is_private": 0,
    "is_purchased": 0,
    "app_id": null,
    "download_count": 348,
    "view_count": 205,
    "education": {
      "grades": [],
      "subjects": []
    },
    "remix_count": 0,
    "make_count": 0,
    "app_count": 4,
    "root_comment_count": 0,
    "moderation": "",
    "is_derivative": false,
    "ancestors": [],
    "type_name": "Thing",
    "is_banned": false,
    "is_comments_disabled": false,
    "needs_moderation": 0,
    "is_decoy": 0,
    "zip_data": {
      "files": [
        {
          "name": "Short_Locline_mouthstick_holder.stl",
          "url": "https:\/\/cdn.thingiverse.com\/assets\/b4\/c7\/16\/0e\/b6\/Short_Locline_mouthstick_holder.stl"
        }
      ],
      "images": [
        {
          "name": "Locline_mouthstick_holder.JPG",
          "url": "https:\/\/cdn.thingiverse.com\/assets\/df\/db\/22\/12\/da\/Locline_mouthstick_holder.JPG"
        },
        {
          "name": "Short_Locline_mouthstick_holder.png",
          "url": "https:\/\/cdn.thingiverse.com\/assets\/0e\/06\/cc\/e8\/7e\/Short_Locline_mouthstick_holder.png"
        }
      ]
    }
  }
}